antelope/__init__.py
antelope/antelope.py
antelope/gen2/.gitignore
antelope/gen2/YAML.interp
antelope/gen2/YAML.tokens
antelope/gen2/YAMLLexer.interp
antelope/gen2/YAMLLexer.py
antelope/gen2/YAMLLexer.tokens
antelope/gen2/YAMLListener.py
antelope/gen2/YAMLParser.py
antelope/gen2/__init__.py
antelope/gen3/.gitignore
antelope/gen3/YAML.interp
antelope/gen3/YAML.tokens
antelope/gen3/YAMLLexer.interp
antelope/gen3/YAMLLexer.py
antelope/gen3/YAMLLexer.tokens
antelope/gen3/YAMLListener.py
antelope/gen3/YAMLParser.py
antelope/gen3/__init__.py
antelope-0.1.dist-info/METADATA
antelope-0.1.dist-info/WHEEL
antelope-0.1.dist-info/top_level.txt
antelope-0.1.dist-info/RECORD
